spsdk/__init__.py
spsdk/__version__.py
spsdk/exceptions.py
spsdk/py.typed
spsdk/versioning.py
spsdk/apps/README.md
spsdk/apps/__init__.py
spsdk/apps/blhost.py
spsdk/apps/blhost_helper.py
spsdk/apps/dk6prog.py
spsdk/apps/el2go.py
spsdk/apps/lpcprog.py
spsdk/apps/nxpcrypto.py
spsdk/apps/nxpdebugmbox.py
spsdk/apps/nxpdevhsm.py
spsdk/apps/nxpdevscan.py
spsdk/apps/nxpdice.py
spsdk/apps/nxpele.py
spsdk/apps/nxpfuses.py
spsdk/apps/nxpimage.py
spsdk/apps/nxpmemcfg.py
spsdk/apps/nxpshe.py
spsdk/apps/nxpuuu.py
spsdk/apps/nxpwpc.py
spsdk/apps/pfr.py
spsdk/apps/sdphost.py
spsdk/apps/sdpshost.py
spsdk/apps/shadowregs.py
spsdk/apps/spsdk_apps.py
spsdk/apps/el2go_apps/common.py
spsdk/apps/el2go_apps/el2go_dev.py
spsdk/apps/el2go_apps/el2go_prod.py
spsdk/apps/el2go_apps/el2go_utils.py
spsdk/apps/nxpele_apps/nxpele_hse.py
spsdk/apps/nxpimage_apps/__init__.py
spsdk/apps/nxpimage_apps/nxpimage_ahab.py
spsdk/apps/nxpimage_apps/nxpimage_bca.py
spsdk/apps/nxpimage_apps/nxpimage_bee.py
spsdk/apps/nxpimage_apps/nxpimage_bimg.py
spsdk/apps/nxpimage_apps/nxpimage_cert_block.py
spsdk/apps/nxpimage_apps/nxpimage_fcf.py
spsdk/apps/nxpimage_apps/nxpimage_hab.py
spsdk/apps/nxpimage_apps/nxpimage_hse.py
spsdk/apps/nxpimage_apps/nxpimage_iee.py
spsdk/apps/nxpimage_apps/nxpimage_lpcprog.py
spsdk/apps/nxpimage_apps/nxpimage_mbi.py
spsdk/apps/nxpimage_apps/nxpimage_otfad.py
spsdk/apps/nxpimage_apps/nxpimage_sb.py
spsdk/apps/nxpimage_apps/nxpimage_signed_msg.py
spsdk/apps/nxpimage_apps/nxpimage_trustzone.py
spsdk/apps/nxpimage_apps/nxpimage_utils.py
spsdk/apps/utils/__init__.py
spsdk/apps/utils/common_cli_options.py
spsdk/apps/utils/interface_helper.py
spsdk/apps/utils/spsdk_logger.py
spsdk/apps/utils/utils.py
spsdk/crypto/__init__.py
spsdk/crypto/_oscca_asn1.py
spsdk/crypto/_otps_puk.py
spsdk/crypto/certificate.py
spsdk/crypto/cmac.py
spsdk/crypto/cms.py
spsdk/crypto/crc.py
spsdk/crypto/crypto_types.py
spsdk/crypto/dilithium.py
spsdk/crypto/exceptions.py
spsdk/crypto/hash.py
spsdk/crypto/hkdf.py
spsdk-3.6.0.dist-info/licenses/LICENSE
spsdk-3.6.0.dist-info/METADATA
spsdk-3.6.0.dist-info/WHEEL
spsdk-3.6.0.dist-info/entry_points.txt
spsdk-3.6.0.dist-info/top_level.txt
spsdk-3.6.0.dist-info/RECORD
